mutablekeysdict/__init__.py
mutablekeysdict/mutablekeysdict.py
mutablekeysdict-0.1.1.dist-info/METADATA
mutablekeysdict-0.1.1.dist-info/WHEEL
mutablekeysdict-0.1.1.dist-info/top_level.txt
mutablekeysdict-0.1.1.dist-info/RECORD
